task_manager/__init__.py
task_manager/common_cli.py
task_manager/common_api/__init__.py
task_manager/common_api/Api/__init__.py
task_manager/common_api/Api/custom_openapi.py
task_manager/common_api/Api/auth_controller/__init__.py
task_manager/common_api/Api/auth_controller/auth_resources.py
task_manager/common_api/Api/auth_controller/crud.py
task_manager/common_api/Api/auth_controller/dataclases.py
task_manager/common_api/Api/auth_controller/exceptions.py
task_manager/common_api/Api/auth_controller/routines.py
task_manager/common_api/Api/common_controller/__init__.py
task_manager/common_api/Api/common_controller/system_resources.py
task_manager/common_configs/__init__.py
task_manager/common_configs/schema_common_api_conf.py
task_manager/common_configs/schema_db_conf.py
task_manager/common_utils/__init__.py
task_manager/common_utils/common.py
task_manager/common_utils/db_connect.py
task_manager/common_utils/fetch.py
task_manager/common_utils/read_conf.py
task_manager/models/__init__.py
task_manager/models/base.py
task_manager/models/mixins.py
task_manager/models/tables/__init__.py
task_manager/models/tables/users.py
tests/__init__.py
tests/test_auth_api.py
konasova-1.3.dist-info/LICENSE
konasova-1.3.dist-info/METADATA
konasova-1.3.dist-info/WHEEL
konasova-1.3.dist-info/entry_points.txt
konasova-1.3.dist-info/top_level.txt
konasova-1.3.dist-info/RECORD
