Metadata-Version: 2.1
Name: konasova
Version: 1.3
Summary: UNKNOWN
Home-page: UNKNOWN
Author: UNKNOWN
Author-email: UNKNOWN
License: UNKNOWN
Platform: UNKNOWN
Requires-Dist: requests (==2.25.1)
Requires-Dist: configparser (==5.0.2)
Requires-Dist: SQLAlchemy (==1.4.11)
Requires-Dist: psycopg2-binary (==2.8.6)
Requires-Dist: pydantic (==1.6.1)
Requires-Dist: fastapi (==0.63.0)
Requires-Dist: fastapi-restful (==0.2.5)
Requires-Dist: fastapi-sqlalchemy (==0.2.1)
Requires-Dist: fastapi-async-sqlalchemy (==0.3.5)
Requires-Dist: fastapi-migrations (==0.0.4)
Requires-Dist: fastapi-jwt-auth (==0.5.0)
Requires-Dist: orjson (==3.5.2)
Requires-Dist: uvicorn (==0.13.4)
Requires-Dist: passlib (==1.7.4)
Requires-Dist: asyncpg (==0.22.0)
Requires-Dist: sqlalchemy-utils (==0.37.2)
